{"image":{"thresholdImageMatchField":"0.8","firstColorOffsetField":"#101010","imageColorExStartYField":"0","tuseClipBox":"请选择","otherColorOffsetField":"#101010","imageCodeTplBox":"请选择","tuseSizeBox":"1px","limitImageMatchField":"2","imageColorExStartXField":"0","maxLevelImageMatchField":"-1","otherColorThresholdField":"1","cmpColorSucThresholdField":"1","thrField":"0.8","firstColorThresholdField":"1","funcImageMatchBox":"findImageByColor","findMethodImageMatchBox":"5: TM_CCOEFF_NORMED归一化系数匹配法","weakThresholdImageMatchField":"0.7","imageOpencvMatBox":"是"},"currentSelected":1,"color":{"colorOpencvMatBox":"是","orzColorBox":"2: 左上角-从左往右","colorCodeTplBox":"请选择","limitColorField":"2","offsetField":["#101010","#101010","#101010","#101010","#101010","#101010","#101010","#101010","#101010","#101010","#101010","#101010","#101010","#101010","#101010","#101010","#101010","#101010","#101010","#101010","#101010","#101010","#101010","#101010","#101010","#101010","#101010","#101010","#101010","#101010","#101010","#101010","#101010","#101010","#101010","#101010","#101010","#101010","#101010","#101010","#101010","#101010","#101010","#101010","#101010","#101010","#101010","#101010","#101010","#101010","#101010","#101010","#101010","#101010","#101010","#101010","#101010","#101010","#101010","#101010","#101010","#101010","#101010","#101010","#101010","#101010","#101010","#101010","#101010","#101010","#101010","#101010","#101010","#101010","#101010","#101010","#101010","#101010","#101010","#101010","#101010","#101010","#101010","#101010","#101010","#101010","#101010","#101010","#101010","#101010","#101010","#101010","#101010","#101010","#101010","#101010","#101010","#101010","#101010","#101010"],"findColorModelBox":"1: 老算法","pianseColorField":"#101010","funcColorBox":"findColor","jingduColorField":"0.9","genCodeModelBox":"1: 字符串模式"},"ocr":{"maxSideLenField":"","ocrTypeBox":"paddleOcrNcnnV5","paddingField":"","releaseOcrBox":"否"}}